create_daca/__init__.py
create_daca/cli.py
create_daca/template/readme.md
create_daca/template/agent_memory_service/.env.example
create_daca/template/agent_memory_service/.python-version
create_daca/template/agent_memory_service/README.md
create_daca/template/agent_memory_service/main.py
create_daca/template/agent_memory_service/models.py
create_daca/template/agent_memory_service/pyproject.toml
create_daca/template/agent_memory_service/test_main.py
create_daca/template/agent_memory_service/uv.lock
create_daca/template/chat_service/.env.example
create_daca/template/chat_service/.python-version
create_daca/template/chat_service/README.md
create_daca/template/chat_service/main.py
create_daca/template/chat_service/models.py
create_daca/template/chat_service/pyproject.toml
create_daca/template/chat_service/test_main.py
create_daca/template/chat_service/uv.lock
create_daca/template/components/pubsub.yaml
create_daca/template/components/statestore.yaml
create_daca/template/components/subscriptions.yaml
create_daca-0.1.2.dist-info/METADATA
create_daca-0.1.2.dist-info/WHEEL
create_daca-0.1.2.dist-info/entry_points.txt
create_daca-0.1.2.dist-info/licenses/LICENSE
create_daca-0.1.2.dist-info/RECORD
